{"capital_utilization":{"average_cash_percent":0.9736310900083912,"average_exposure_percent":0.026368909991608746,"average_leverage":0.026368909991608746,"average_position_value":192.69924694892475,"max_exposure_percent":0.41329896927534526},"closed_trades":6,"equity_curve":[],"final_equity":485.3995173347057,"max_drawdown":0.08846875589483512,"open_trades":0,"profit_factor":0.5972172375632399,"sharpe":-0.429345368158651,"signal_diagnostics":{"buy_signals":6,"duplicate_buy_skips":0,"flat_sell_skips":0,"hold_signals":428,"risk_blocked_signals":0,"sell_signals":0,"stop_loss_exits":4,"take_profit_exits":2},"starting_equity":500,"total_return":-0.02920096533058858,"trade_analysis":{"average_loss":-9.062256399059963,"average_trade_duration_days":5.666666666666667,"average_win":10.82427146547277,"expectancy":-2.433413777549052,"largest_loss":-15.935056335952021,"largest_win":11.187714246698505,"max_trade_duration_days":7.0,"median_trade_duration_days":6.0,"profit_factor":0.5972172375632399,"time_in_market_percent":0.05328805590021551,"total_trades":6,"win_rate":0.3333333333333333}}